cf_netSDM/__init__.py
cf_netSDM/interaction_views.py
cf_netSDM/library.py
cf_netSDM/library_cli.py
cf_netSDM/requirements.txt
cf_netSDM/urls.py
cf_netSDM/views.py
cf_netSDM/visualization_views.py
cf_netSDM/lib/HIN.py
cf_netSDM/lib/__init__.py
cf_netSDM/lib/converters.py
cf_netSDM/lib/core.py
cf_netSDM/lib/decomposition.py
cf_netSDM/lib/helpers.py
cf_netSDM/lib/settings.py
cf_netSDM/lib/assets/builtin.n3
cf_netSDM/package_data/categories/1ff6ffa5-dee7-4f59-9d8f-1986cd2811e6.json
cf_netSDM/package_data/widgets/349dabfc-b54b-40be-86b2-2403cfc4f4fa.json
cf_netSDM/package_data/widgets/34fa8bd5-64c5-4400-abf2-ba0d90568980.json
cf_netSDM/package_data/widgets/81ca1c91-e8a7-4f4f-b890-ce32720d8403.json
cf_netSDM/package_data/widgets/c3b7ff9a-8de1-4497-90fa-8e541aed4c6c.json
cf_netSDM/package_data/widgets/e23ceba8-7d67-46a7-8a51-b2929c4a4e39.json
cf_netSDM/templates/interactions/hinmine_decompose_interact.html
cf_netSDM-0.0.3.dist-info/LICENSE.md
cf_netSDM-0.0.3.dist-info/METADATA
cf_netSDM-0.0.3.dist-info/WHEEL
cf_netSDM-0.0.3.dist-info/top_level.txt
cf_netSDM-0.0.3.dist-info/RECORD
