Metadata-Version: 2.1
Name: cf-netSDM
Version: 0.0.3
Summary: ClowdFlows 3 module for network analysis for semantic data mining
Home-page: https://github.com/JanKralj/cf_netSDM
Author: Jan Kralj
Author-email: jan.kralj@ijs.si
License: MIT License
Platform: UNKNOWN
Classifier: Development Status :: 2 - Pre-Alpha
Classifier: Environment :: Web Environment
Classifier: Framework :: Django
Classifier: Intended Audience :: Developers
Classifier: License :: OSI Approved :: MIT License
Classifier: Operating System :: OS Independent
Classifier: Programming Language :: Python
Classifier: Programming Language :: Python :: 3
Requires-Dist: numpy (>=1.7.1)
Requires-Dist: rdflib (>=4.2.2)
Requires-Dist: Orange (==3.7.0)
